cdtPy/__init__.py
cdtPy/geoGrd.py
cdtPy/oceAtm.py
cdtPy-1.0.0.dist-info/METADATA
cdtPy-1.0.0.dist-info/WHEEL
cdtPy-1.0.0.dist-info/top_level.txt
cdtPy-1.0.0.dist-info/RECORD
